FSM-Structural/jkff.v
module jkff(input clk, input reset, input j, input k, output reg q);
    always @ (posedge clk) begin
        if (reset == 1'b1) begin
            q <= 0;
        end
        else begin
            if (j == 1'b0 && k == 1'b0) q <= q;
            else if (j == 1'b1 && k == 1'b0) q <= 1;
            else if (j == 1'b0 && k == 1'b1) q <= 0;
            else q <= ~q;
        end
    end
endmodule

FSM-Structural/fsm.v
`include "jkff.v"
module fsm(input clk, input reset, input in, output reg out);
    wire j, k;
    wire state;
    assign j = in;
    assign k = ~in;
    jkff jk (clk, reset, j, k, state);
    always @ (in, state) begin
        out = state && ~in;
    end
endmodule

FSM-Structural/fsm_tb.v
`include "fsm.v"

module fsm_tb;
reg clk, reset, in;
wire out;

fsm q (clk, reset, in, out);

always #5 clk = ~clk;

initial begin
    $dumpfile("out.vcd");
    $dumpvars(0, fsm_tb);
    clk = 0; reset = 1; in = 0;
    #10 reset = 0;
    #10 in = 0;
    #10 in = 0;
    #10 in = 1;
    #10 in = 0;
    #10 in = 0;
    #10 in = 1;
    #10 in = 0;
    #10 $finish;
end

initial begin
    $monitor("time: %0t | in: %b | out: %b", $time, in, out);
end
endmodule

FSM-Structural/out.vcd
$date
	Mon Oct 14 00:59:22 2024
$end
$version
	Icarus Verilog
$end
$timescale
	1s
$end
$scope module fsm_tb $end
$var wire 1 ! out $end
$var reg 1 " clk $end
$var reg 1 # in $end
$var reg 1 $ reset $end
$scope module q $end
$var wire 1 " clk $end
$var wire 1 # in $end
$var wire 1 % j $end
$var wire 1 & k $end
$var wire 1 $ reset $end
$var wire 1 ' state $end
$var reg 1 ! out $end
$scope module jk $end
$var wire 1 " clk $end
$var wire 1 % j $end
$var wire 1 & k $end
$var wire 1 $ reset $end
$var reg 1 ' q $end
$upscope $end
$upscope $end
$upscope $end
$enddefinitions $end
$comment Show the parameter values. $end
$dumpall
$end
#0
$dumpvars
x'
1&
0%
1$
0#
0"
x!
$end
#5
0!
0'
1"
#10
0"
0$
#15
1"
#20
0"
#25
1"
#30
0"
#35
1"
#40
0&
0"
1%
1#
#45
1'
1"
#50
1&
1!
0"
0%
0#
#55
0!
0'
1"
#60
0"
#65
1"
#70
0&
0"
1%
1#
#75
1'
1"
#80
1&
1!
0"
0%
0#
#85
0!
0'
1"
