Tutorial-1/function.v
module func (out, A, B, C, D);

output out;
input A, B, C, D;

assign out = (!A && !B && !C && !D) || (A && !C && !D) || (!B && C && !D) || (!A && B && C && D) || (B && !C && D);

endmodule

Tutorial-1/testbench.v
`include "function.v"

module t_func;
wire t_out;
reg t_A, t_B, t_C, t_D;
parameter stop_time = 200;

func F1 (t_out, t_A, t_B, t_C, t_D);

initial #stop_time $finish;
    initial begin
    $dumpfile("out.vcd");
    $dumpvars(0, t_func);
        t_A = 0; t_B = 0; t_C = 0; t_D = 0;
    #10 t_A = 0; t_B = 0; t_C = 0; t_D = 1;
    #10 t_A = 0; t_B = 0; t_C = 1; t_D = 0;
    #10 t_A = 0; t_B = 0; t_C = 1; t_D = 1;
    #10 t_A = 0; t_B = 1; t_C = 0; t_D = 0;
    #10 t_A = 0; t_B = 1; t_C = 0; t_D = 1;
    #10 t_A = 0; t_B = 1; t_C = 1; t_D = 0;
    #10 t_A = 0; t_B = 1; t_C = 1; t_D = 1;
    #10 t_A = 1; t_B = 0; t_C = 0; t_D = 0;
    #10 t_A = 1; t_B = 0; t_C = 0; t_D = 1;
    #10 t_A = 1; t_B = 0; t_C = 1; t_D = 0;
    #10 t_A = 1; t_B = 0; t_C = 1; t_D = 1;
    #10 t_A = 1; t_B = 1; t_C = 0; t_D = 0;
    #10 t_A = 1; t_B = 1; t_C = 0; t_D = 1;
    #10 t_A = 1; t_B = 1; t_C = 1; t_D = 0;
    #10 t_A = 1; t_B = 1; t_C = 1; t_D = 1;
    end

    initial begin
        $monitor("time = %0d A = %b B = %b C=%b D=%b OUT = %b", $time, t_A, t_B, t_C, t_D, t_out);
    end
endmodule

Tutorial-1/out.vcd
$date
	Thu Aug 29 08:51:20 2024
$end
$version
	Icarus Verilog
$end
$timescale
	1s
$end
$scope module t_func $end
$var wire 1 ! t_out $end
$var parameter 32 " stop_time $end
$var reg 1 # t_A $end
$var reg 1 $ t_B $end
$var reg 1 % t_C $end
$var reg 1 & t_D $end
$scope module F1 $end
$var wire 1 # A $end
$var wire 1 $ B $end
$var wire 1 % C $end
$var wire 1 & D $end
$var wire 1 ! out $end
$upscope $end
$upscope $end
$enddefinitions $end
$comment Show the parameter values. $end
$dumpall
b11001000 "
$end
#0
$dumpvars
0&
0%
0$
0#
1!
$end
#10
0!
1&
#20
1!
0&
1%
#30
0!
1&
#40
0&
0%
1$
#50
1!
1&
#60
0!
0&
1%
#70
1!
1&
#80
1!
0&
0%
0$
1#
#90
0!
1&
#100
1!
0&
1%
#110
0!
1&
#120
1!
0&
0%
1$
#130
1&
#140
0!
0&
1%
#150
1&
