Lab4/mux_2to1.v
module mux_2to1 (input[1:0] i, input s, output out);
    wire[1:0] temp;
    and a1 (temp[0], i[0], !s);
    and a2 (temp[1], i[1], s);
    or o1 (out, temp[0], temp[1]);
endmodule

Lab4/mux_2to1_tb.v
`include "mux_2to1.v"

module mux_2to1_tb ();

wire out;
reg[1:0] in;
reg s;

mux_2to1 mux (in, s, out);

initial begin
    $dumpfile("mux_2to1.vcd");
    $dumpvars(0, mux_2to1_tb);
        in = 2'b00; s = 0;
    #10 in = 2'b00; s = 1;
    #10 in = 2'b01; s = 0;
    #10 in = 2'b01; s = 1;
    #10 in = 2'b10; s = 0;
    #10 in = 2'b10; s = 1;
    #10 in = 2'b11; s = 0;
    #10 in = 2'b11; s = 1;
end

initial begin
    $monitor("time=%2d | in=%b%b s=%b | out=%b", $time, in[1], in[0], s, out);
end

endmodule

Lab4/mux_2to1.vcd
$date
	Sun Sep 08 15:57:05 2024
$end
$version
	Icarus Verilog
$end
$timescale
	1s
$end
$scope module mux_2to1_tb $end
$var wire 1 ! out $end
$var reg 2 " in [1:0] $end
$var reg 1 # s $end
$scope module mux $end
$var wire 2 $ i [1:0] $end
$var wire 1 ! out $end
$var wire 1 # s $end
$var wire 2 % temp [1:0] $end
$upscope $end
$upscope $end
$enddefinitions $end
$comment Show the parameter values. $end
$dumpall
$end
#0
$dumpvars
b0 %
b0 $
0#
b0 "
0!
$end
#10
1#
#20
1!
b1 %
0#
b1 "
b1 $
#30
0!
b0 %
1#
#40
0#
b10 "
b10 $
#50
1!
b10 %
1#
#60
b1 %
0#
b11 "
b11 $
#70
b10 %
1#
