Lab4/decoder_2to4.v
module decoder_2to4 (input[1:0] in, input e, output[3:0] out);
    and a1 (out[0], !in[0], !in[1], e);
    and a2 (out[1], in[0], !in[1], e);
    and a3 (out[2], !in[0], in[1], e);
    and a4 (out[3], in[0], in[1], e);
endmodule

Lab4/decoder_3to8.v
`include "decoder_2to4.v"

module decoder_3to8 (input[2:0] in, output[7:0] out);
    decoder_2to4 d1 (in[1:0], !in[2], out[3:0]);
    decoder_2to4 d2 (in[1:0], in[2], out[7:4]);
endmodule

Lab4/testbench.v
`include "decoder_3to8.v"

module testbench ();
    reg[2:0] in;
    wire[7:0] out;

    decoder_3to8 d (in, out);

    initial begin
        $dumpfile("testbench.vcd");
        $dumpvars(0, testbench);
            in = 3'b000;
        #10 in = 3'b001;
        #10 in = 3'b010;
        #10 in = 3'b011;
        #10 in = 3'b100;
        #10 in = 3'b101;
        #10 in = 3'b110;
        #10 in = 3'b111;
    end

    initial begin
        $monitor("TIME = %2d | INPUT = %b%b%b | OUTPUT = %b%b%b%b%b%b%b%b", $time, in[2], in[1], in[0], out[7], out[6], out[5], out[4], out[3], out[2], out[1], out[0]);
    end
endmodule

Lab4/testbench.vcd
$date
	Sun Sep 08 17:08:08 2024
$end
$version
	Icarus Verilog
$end
$timescale
	1s
$end
$scope module testbench $end
$var wire 8 ! out [7:0] $end
$var reg 3 " in [2:0] $end
$scope module d $end
$var wire 3 # in [2:0] $end
$var wire 8 $ out [7:0] $end
$scope module d1 $end
$var wire 1 % e $end
$var wire 2 & in [1:0] $end
$var wire 4 ' out [3:0] $end
$upscope $end
$scope module d2 $end
$var wire 1 ( e $end
$var wire 2 ) in [1:0] $end
$var wire 4 * out [3:0] $end
$upscope $end
$upscope $end
$upscope $end
$enddefinitions $end
$comment Show the parameter values. $end
$dumpall
$end
#0
$dumpvars
b0 *
b0 )
0(
b1 '
b0 &
1%
b1 $
b0 #
b0 "
b1 !
$end
#10
b10 !
b10 $
b10 '
b1 &
b1 )
b1 "
b1 #
#20
b100 !
b100 $
b100 '
b10 &
b10 )
b10 "
b10 #
#30
b1000 !
b1000 $
b1000 '
b11 &
b11 )
b11 "
b11 #
#40
b0 '
b10000 !
b10000 $
b1 *
b0 &
0%
b0 )
1(
b100 "
b100 #
#50
b100000 !
b100000 $
b10 *
b1 &
b1 )
b101 "
b101 #
#60
b1000000 !
b1000000 $
b100 *
b10 &
b10 )
b110 "
b110 #
#70
b10000000 !
b10000000 $
b1000 *
b11 &
b11 )
b111 "
b111 #
