Lab6-Solutions/dff_async.v
module dff_async_reset (input clk,input reset,input d,output reg q);
    // WRITE YOUR CODE HERE
    always @(posedge clk or negedge reset) begin
        if(reset)begin
            q <= d;
        end
        else if(reset==1'b0)begin
            q <= 1'b0;
        end
    end
endmodule

Flipflops/jkff.v
`include "dff_asycr.v"

module jkff_asycr(input j, input k, input clk, input reset, output q);
    wire q_n, d;
    wire[1:0] temp;
    not n1 (q_n, q);
    and a1 (temp[0], q_n, j);
    and a2 (temp[1], q, k);
    or o1 (d, temp[0], temp[1]);
    dff_async_reset dff (clk, reset, d, q);
endmodule

module jkff_behavioural(input j, input k, input clk, output reg q);
    always @ (posedge clk) begin
        if (j == 1'b1 && k == 1'b0) begin
            q <= 1;
        end
        else if (j == 1'b0 && k == 1'b1) begin
            q <= 0;
        end
        else if (j == 1'b1 && k == 1'b1) begin
            q <= ~q;
        end
    end
endmodule

Flipflops/jkff_testbench.v
`include "jkff.v"

module jkff_testbench;
    reg j, k, clk, reset;
    wire q;
    jkff_asycr jkff (.j(j), .k(k), .clk(clk), .reset(reset), .q(q));
    always begin
        #5 clk = ~clk;
    end
    initial begin
        clk = 0;
        reset = 0; j = 0; k= 0;
        $dumpfile("out.vcd");
        $dumpvars(0, jkff_testbench);
        #10 j = 1; k = 0;
        #10 reset = 1;
        #10 reset = 0;
        #10 j = 1; k = 0;
        #10 j = 0; k = 1;
        #10 j = 0; k = 0;
        #10 j = 1; k = 1;
        #10 $finish;
    end
endmodule

Flipflops/out.vcd
$date
	Mon Sep 23 01:52:03 2024
$end
$version
	Icarus Verilog
$end
$timescale
	1s
$end
$scope module jkff_testbench $end
$var wire 1 ! q $end
$var reg 1 " clk $end
$var reg 1 # j $end
$var reg 1 $ k $end
$var reg 1 % reset $end
$scope module jkff $end
$var wire 1 " clk $end
$var wire 1 & d $end
$var wire 1 # j $end
$var wire 1 $ k $end
$var wire 1 ' q_n $end
$var wire 1 % reset $end
$var wire 2 ( temp [1:0] $end
$var wire 1 ! q $end
$scope module dff $end
$var wire 1 " clk $end
$var wire 1 & d $end
$var wire 1 % reset $end
$var reg 1 ! q $end
$upscope $end
$upscope $end
$upscope $end
$enddefinitions $end
$comment Show the parameter values. $end
$dumpall
$end
#0
$dumpvars
b0 (
x'
0&
0%
0$
0#
0"
x!
$end
#5
1'
0!
1"
#10
1&
b1 (
0"
1#
#15
0&
b0 (
0'
1!
1"
#20
1&
b1 (
1'
0!
0"
1%
#25
1"
#30
0"
0%
#35
0&
b0 (
0'
1!
1"
#40
0"
#45
1&
b1 (
1'
0!
1"
#50
0&
b0 (
0"
1$
0#
#55
1"
#60
0"
0$
#65
1"
#70
1&
b1 (
0"
1$
1#
#75
b10 (
0'
1!
1"
