Flipflops/tff_asr.v
`include "dff_asycr.v"
module tff (
    input clk,
    input reset,
    input t,
    output q
);
    wire d;
    xor x1(d, q, t);
  dff_async_reset dff (clk, reset, d, q);  

endmodule

module tff_behavioral (input clk, 
input reset, 
input t, 
output reg q);

always @(posedge clk or posedge reset) begin
    if (reset)
        q<=1'b0;
    else if (t)
        q<=~q;
end

endmodule

Flipflops/testbench_tff.v
`include "tff_asr.v"

module tff_async_reset_tb;

    reg clk;
    reg reset;
    reg t;
    wire q;

    tff_behavioral uut (
        .clk(clk),
        .reset(reset),
        .t(t),
        .q(q)
    );

    always #10 clk = ~clk;

    initial begin
        clk = 0; reset = 0; t = 0;
        $dumpfile("tff_async_reset_tb.vcd");
        $dumpvars(0, tff_async_reset_tb);

        reset = 1; #20; reset = 0;

        t = 1; #40;
        t = 0; #40;
        t = 1; #40;

        reset = 1; #20; reset = 0;

        t = 1; #40;

        $finish;
    end

    initial begin
        $monitor("Time: %0t | clk: %b | reset: %b | t: %b | q: %b", $time, clk, reset, t, q);
    end

endmodule

Flipflops/tff_async_reset_tb.vcd
$date
	Thu Sep 19 08:42:52 2024
$end
$version
	Icarus Verilog
$end
$timescale
	1s
$end
$scope module tff_async_reset_tb $end
$var wire 1 ! q $end
$var reg 1 " clk $end
$var reg 1 # reset $end
$var reg 1 $ t $end
$scope module uut $end
$var wire 1 " clk $end
$var wire 1 # reset $end
$var wire 1 $ t $end
$var reg 1 ! q $end
$upscope $end
$upscope $end
$enddefinitions $end
$comment Show the parameter values. $end
$dumpall
$end
#0
$dumpvars
0$
1#
0"
0!
$end
#10
1"
#20
0"
1$
0#
#30
1!
1"
#40
0"
#50
0!
1"
#60
0"
0$
#70
1"
#80
0"
#90
1"
#100
0"
1$
#110
1!
1"
#120
0"
#130
0!
1"
#140
0"
1#
#150
1"
#160
0"
0#
#170
1!
1"
#180
0"
#190
0!
1"
